LICENSE.txt
MANIFEST.in
README.rst
build_required_packages.req
example.py
readme.md
required_packages.req
setup.py
testService.ps1
test_required_packages.req
pywinservicemanager/ConfigurationTypes.py
pywinservicemanager/NewServiceDefinition.py
pywinservicemanager/ServiceConfigurations.py
pywinservicemanager/ServiceConfigurations2.py
pywinservicemanager/ServiceEntity.py
pywinservicemanager/ServiceStatusEntity.py
pywinservicemanager/ServiceStatusProcessEntity.py
pywinservicemanager/WindowsServiceConfigurationManager.py
pywinservicemanager/__init__.py
pywinservicemanager.egg-info/PKG-INFO
pywinservicemanager.egg-info/SOURCES.txt
pywinservicemanager.egg-info/dependency_links.txt
pywinservicemanager.egg-info/top_level.txt
pywinservicemanager/tests/TestBinaryPathNameType.py
pywinservicemanager/tests/TestCurrentStateType.py
pywinservicemanager/tests/TestDelayedAutoStartInfoType.py
pywinservicemanager/tests/TestDependenciesType.py
pywinservicemanager/tests/TestDescriptionType.py
pywinservicemanager/tests/TestDisplayNameType.py
pywinservicemanager/tests/TestErrorControlType.py
pywinservicemanager/tests/TestFailureActionConfigurationCommandLineType.py
pywinservicemanager/tests/TestFailureActionConfigurationRebootMessageType.py
pywinservicemanager/tests/TestFailureActionConfigurationResetPeriodType.py
pywinservicemanager/tests/TestFailureActionConfigurationType.py
pywinservicemanager/tests/TestFailureActionDelayType.py
pywinservicemanager/tests/TestFailureActionExecutionType.py
pywinservicemanager/tests/TestFailureActionType.py
pywinservicemanager/tests/TestFailureFlagType.py
pywinservicemanager/tests/TestLoadOrderGroupType.py
pywinservicemanager/tests/TestPreShutdownInfoType.py
pywinservicemanager/tests/TestServiceConfigurations.py
pywinservicemanager/tests/TestServiceConfigurations2.py
pywinservicemanager/tests/TestServiceNameType.py
pywinservicemanager/tests/TestServiceSIDInfoType.py
pywinservicemanager/tests/TestServiceStartNameType.py
pywinservicemanager/tests/TestServiceStartType.py
pywinservicemanager/tests/TestServiceType.py
pywinservicemanager/tests/__init__.py