Metadata-Version: 1.0
Name: pywinservicemanager
Version: 1.1.1
Summary: Windows Service Manager Module that wraps for the win32service api
Home-page: https://github.com/belvedere-trading/pywinservicemanager
Author: Team Belvedere, LLC
Author-email: opensource@belvederetrading.com
License: PyWinServiceManager - Wrapper for the win32service api
